softrader/__init__.py
softrader/Model.ipynb
softrader/Others.ipynb
softrader-0.1.5.dist-info/METADATA
softrader-0.1.5.dist-info/WHEEL
softrader-0.1.5.dist-info/RECORD
