Metadata-Version: 2.3
Name: softrader
Version: 0.1.5
Summary: All-in-one trading broker software
Author: Jose_Henrique_V
Requires-Python: >=3.11
Classifier: Programming Language :: Python :: 3
Classifier: Programming Language :: Python :: 3.11
Classifier: Programming Language :: Python :: 3.12
Classifier: Programming Language :: Python :: 3.13
Requires-Dist: MetaTrader5 (==5.0.4874)
Requires-Dist: alpaca-py (==0.39.1)
Requires-Dist: ib_insync (==0.9.86)
